kivy_css/__init__.py
kivy_css/css_parser.py
kivyandcss-1.1.dist-info/LICENSE
kivyandcss-1.1.dist-info/METADATA
kivyandcss-1.1.dist-info/WHEEL
kivyandcss-1.1.dist-info/top_level.txt
kivyandcss-1.1.dist-info/RECORD
