Metadata-Version: 2.1
Name: kivyandcss
Version: 1.1
Summary: A CSS-like styling library for Kivy applications
Home-page: https://github.com/hqmdokkai/kivyandcss
Author: Bobby
Author-email: akirasumeragi699@gmail.com
Classifier: Programming Language :: Python :: 3
Classifier: License :: OSI Approved :: MIT License
Classifier: Operating System :: OS Independent
Requires-Python: >=3.6
License-File: LICENSE
Requires-Dist: kivy
